LICENSE
README.rst
setup.py
pyzuoyz/__init__.py
pyzuoyz/metrics.py
pyzuoyz/prompt.py
pyzuoyz/scaled_rope.py
pyzuoyz.egg-info/PKG-INFO
pyzuoyz.egg-info/SOURCES.txt
pyzuoyz.egg-info/dependency_links.txt
pyzuoyz.egg-info/requires.txt
pyzuoyz.egg-info/top_level.txt